CHANGELOG
COPYRIGHT
LICENSE.rst
MANIFEST.in
README.md
fastapi_tryton.py
setup.cfg
setup.py
version.py
fastapi_tryton.egg-info/PKG-INFO
fastapi_tryton.egg-info/SOURCES.txt
fastapi_tryton.egg-info/dependency_links.txt
fastapi_tryton.egg-info/not-zip-safe
fastapi_tryton.egg-info/requires.txt
fastapi_tryton.egg-info/top_level.txt